mceliece/__init__.py
mceliece/_lib.py
mceliece/kem.py
mceliece-20241009.1.dist-info/licenses/LICENSE
mceliece-20241009.1.dist-info/METADATA
mceliece-20241009.1.dist-info/WHEEL
mceliece-20241009.1.dist-info/top_level.txt
mceliece-20241009.1.dist-info/RECORD
