Metadata-Version: 2.4
Name: mceliece
Version: 20241009.1
Summary: Python wrapper around implementation of the Classic Mceliece cryptosystems
Author-email: Jan Mojžíš <jan.mojzis@gmail.com>
License: Creative Commons Legal Code
Requires-Python: >=3.7
License-File: LICENSE
Dynamic: license-file
